pypalazzetti/__init__.py
pypalazzetti/client.py
pypalazzetti/config.py
pypalazzetti/const.py
pypalazzetti/exceptions.py
pypalazzetti/fan.py
pypalazzetti/state.py
pypalazzetti/temperature.py
pypalazzetti-0.1.20.dist-info/licenses/LICENSE
pypalazzetti-0.1.20.dist-info/METADATA
pypalazzetti-0.1.20.dist-info/WHEEL
pypalazzetti-0.1.20.dist-info/top_level.txt
pypalazzetti-0.1.20.dist-info/RECORD
