Metadata-Version: 2.4
Name: pypalazzetti
Version: 0.1.20
Summary: A Python library to access and control a Palazzetti stove through a Palazzetti Connection Box
Home-page: https://github.com/dotvav/py-palazzetti-api
Author: Vincent Roukine
Author-email: vincent.roukine@gmail.com
License: MIT
Requires-Python: >=3.10
License-File: LICENSE
Requires-Dist: aiohttp>=3.10.3
Dynamic: author
Dynamic: author-email
Dynamic: description
Dynamic: description-content-type
Dynamic: home-page
Dynamic: license
Dynamic: license-file
Dynamic: requires-dist
Dynamic: requires-python
Dynamic: summary
